pytest_lw_realtime_result.py
pytest_lw_realtime_result-0.1.0.dist-info/METADATA
pytest_lw_realtime_result-0.1.0.dist-info/WHEEL
pytest_lw_realtime_result-0.1.0.dist-info/entry_points.txt
pytest_lw_realtime_result-0.1.0.dist-info/top_level.txt
pytest_lw_realtime_result-0.1.0.dist-info/RECORD
